Workbook

Sheet Calculadora base
F5: Cambio oficial dólar a códoba | G5: 36.62
A6: TABLA DE COSTOS
A7: Producto | B7: Peso del producto en Kg | C7: Peso Unitario (libras) | D7: Peso total en Kg | E7: Peso total (libras) | F7: Cantidad | G7: Costo Unitario ($) | H7: Costo Total | I7: comisión sobre transacción | J7: costo de envío interno en china | K7: Costo total total al almacen | L7: Costo Envío China-USA | M7: Costo Envío USA-NIC ($) | N7: Costo envío Total ($) | O7: Costo Total Lote ($) | P7: Costo Unitario NIC | Q7: Precio de venta | R7: Ingreso total por producto | S7: utilidad por producto | T7: margen sobre costros por producto | U7: margen sobre ventas por productos | V7: Links
B8: 0.5 | C8: ='Calculadora base'!$B8*2.2 -> 1.1 | D8: ='Calculadora base'!$F8*'Calculadora base'!$B8 -> 5 | E8: ='Calculadora base'!$D8*2.2 -> 11 | F8: 10 | G8: 7.5 | H8: ='Calculadora base'!$F8*'Calculadora base'!$G8 -> 75 | I8: ='Calculadora base'!$H8*0.0295 -> 2.2125 | J8: ='Calculadora base'!$H8*0.03 -> 2.25 | K8: =SUM('Calculadora base'!$H8,'Calculadora base'!$I8,'Calculadora base'!$J8) -> 79.4625 | L8: =1.4*'Calculadora base'!$E8 -> 15.4 | M8: ='Calculadora base'!$E8*$E$31 -> 22 | N8: =SUM('Calculadora base'!$L8,'Calculadora base'!$M8) -> 37.4 | O8: =SUM('Calculadora base'!$N8, 'Calculadora base'!$H8, 'Calculadora base'!$I8, 'Calculadora base'!$J8) -> 116.8625 | P8: ='Calculadora base'!$O8/'Calculadora base'!$F8 -> 11.68625 | Q8: 27.2 | R8: ='Calculadora base'!$F8*'Calculadora base'!$Q8 -> 272 | S8: ='Calculadora base'!$R8-'Calculadora base'!$O8 -> 155.1375 | T8: =(('Calculadora base'!$Q8-'Calculadora base'!$P8)/'Calculadora base'!$P8) -> 1.3275217 | U8: =(('Calculadora base'!$Q8-'Calculadora base'!$P8)/'Calculadora base'!$Q8) -> 0.57035846 | V8: Link
B9: 0.1 | C9: ='Calculadora base'!$B9*2.2 -> 0.22 | D9: ='Calculadora base'!$F9*'Calculadora base'!$B9 -> 1.5 | E9: ='Calculadora base'!$D9*2.2 -> 3.3 | F9: 15 | G9: 2.95 | H9: ='Calculadora base'!$F9*'Calculadora base'!$G9 -> 44.25 | I9: ='Calculadora base'!$H9*0.0295 -> 1.305375 | J9: ='Calculadora base'!$H9*0.03 -> 1.3275 | K9: =SUM('Calculadora base'!$H9,'Calculadora base'!$I9,'Calculadora base'!$J9) -> 46.882875 | L9: =1.4*'Calculadora base'!$E9 -> 4.62 | M9: ='Calculadora base'!$E9*$E$31 -> 6.6 | N9: =SUM('Calculadora base'!$L9,'Calculadora base'!$M9) -> 11.22 | O9: =SUM('Calculadora base'!$N9, 'Calculadora base'!$H9, 'Calculadora base'!$I9, 'Calculadora base'!$J9) -> 58.102875 | P9: ='Calculadora base'!$O9/'Calculadora base'!$F9 -> 3.873525 | Q9: 16.26 | R9: ='Calculadora base'!$F9*'Calculadora base'!$Q9 -> 243.9 | S9: ='Calculadora base'!$R9-'Calculadora base'!$O9 -> 185.79712 | T9: =(('Calculadora base'!$Q9-'Calculadora base'!$P9)/'Calculadora base'!$P9) -> 3.1977269 | U9: =(('Calculadora base'!$Q9-'Calculadora base'!$P9)/'Calculadora base'!$Q9) -> 0.76177583 | V9: Link
A17: Total | B17: =SUM(B8:B16) -> 0.6 | C17: =SUM(C8:C16) -> 1.32 | D17: 35 | E17: =SUM(E8:E16) -> 14.3 | F17: =SUM(F8:F16) -> 25 | G17: =SUM(G8:G16) -> 10.45 | H17: =SUM(H8:H16) -> 119.25 | I17: ='Calculadora base'!$H17*0.0295 -> 3.517875 | J17: ='Calculadora base'!$H17*0.03 -> 3.5775 | K17: =SUM('Calculadora base'!$H17,'Calculadora base'!$I17,'Calculadora base'!$J17) -> 126.34538 | L17: =SUM(L8:L16) -> 20.02 | M17: =SUM(M8:M16) -> 28.6 | N17: =SUM(N8:N16) -> 48.62 | O17: =SUM(O8:O16) -> 174.96537 | P17: =SUM(P8:P16) -> 15.559775 | Q17: =SUM(Q8:Q16) -> 43.46 | R17: =SUM(R8:R16) -> 515.9 | S17: =SUM(S8:S16) -> 340.93462
A29: Concepto | B29: Monto (USD)
A30: Ingresos totales por ventas | B30: =R17 -> 515.9 | D30: COSTOS x libra | E30: Cantidad (Dólares)
D31: Envío de productos (USA-NIC) | E31: 2
A32: Costos de operación | D32: Envío de productos (CHN-USA) | E32: 1. 4
A33: - Costo total de productos | B33: =SUM(K8:K15) -> 126.34538
A34: - Costo total de envío | B34: =SUM(N8:N15) -> 48.62
A35: - Gastos de marketing/publicidad | B35: =SUM(O17:O20) -> 174.96537
A36: Costo total de la operación | B36: =SUM(B33:B35) -> 349.93075
A38: Utilidad bruta | B38: =B30-B33-B34 -> 340.93462 | H38: compression sockings 15-20mmHg | I38: beige | J38: black
A39: Utilidad neta | B39: =B38-B35 -> 165.96925 | H39: s | I39: 2 | J39: 2
H40: m | I40: 3 | J40: 3
A41: Márgenes | H41: total | I41: 5 | J41: 5
A42: - Margen bruto sobre ingresos (%) | B42: =B38/B30 -> 0.66085409
A43: - Margen neto sobre ingresos (%) | B43: =B39/B30 -> 0.32170818
A44: - Margen neto sobre costos totales (%) | B44: =B39/B36 -> 0.4742917
K66: .

Sheet Enero
F5: Cambio oficial dólar a códoba | G5: 36.62 | P5: =(P15*2) -> 5.3285 | R5: 4
A6: TABLA DE COSTOS
A7: Producto | B7: Peso del producto en Kg | C7: Peso Unitario (libras) | D7: Peso total en Kg | E7: Peso total (libras) | F7: Cantidad | G7: Costo Unitario ($) | H7: Costo Total | I7: comisión sobre transacción | J7: costo de envío interno en china | K7: Costo total total al almacen | L7: Costo Envío China-USA | M7: Costo Envío USA-NIC ($) | N7: Costo envío Total ($) | O7: Costo Total Lote ($) | P7: Costo Unitario NIC | Q7: Precio de venta | R7: Ingreso total por producto | S7: utilidad por producto | T7: margen sobre costros por producto | U7: margen sobre ventas por productos | V7: Links
A8: Gym bags | B8: 0.53 | C8: =Enero!$B8*2.2 -> 1.166 | D8: =Enero!$F8*Enero!$B8 -> 11.66 | E8: =Enero!$D8*2.2 -> 25.652 | F8: 22 | G8: 5.19 | H8: =Enero!$F8*Enero!$G8 -> 114.18 | I8: =Enero!$H8*0.06 -> 6.8508 | J8: =Enero!$H8*0.035 -> 3.9963 | K8: =SUM(Enero!$H8,Enero!$I8,Enero!$J8) -> 125.0271 | L8: =1.4*Enero!$E8 -> 35.9128 | M8: =Enero!$E8*$E$31 -> 51.304 | N8: =SUM(Enero!$L8,Enero!$M8) -> 87.2168 | O8: =SUM(Enero!$N8, Enero!$H8, Enero!$I8, Enero!$J8) -> 212.2439 | P8: =Enero!$O8/Enero!$F8 -> 9.64745 | Q8: 16 | R8: =Enero!$F8*Enero!$Q8 -> 352 | S8: =Enero!$R8-Enero!$O8 -> 139.7561 | T8: =((Enero!$Q8-Enero!$P8)/Enero!$P8) -> 0.65846934 | U8: =((Enero!$Q8-Enero!$P8)/Enero!$Q8) -> 0.39703437 | V8: Link
A9: Enterizo | B9: 0.1 | C9: =Enero!$B9*2.2 -> 0.22 | D9: =Enero!$F9*Enero!$B9 -> 1.5 | E9: =Enero!$D9*2.2 -> 3.3 | F9: 15 | G9: 3.8 | H9: =Enero!$F9*Enero!$G9 -> 57 | I9: =Enero!$H9*0.06 -> 3.42 | J9: =Enero!$H9*0.035 -> 1.995 | K9: =SUM(Enero!$H9,Enero!$I9,Enero!$J9) -> 62.415 | L9: =1.4*Enero!$E9 -> 4.62 | M9: =Enero!$E9*$E$31 -> 6.6 | N9: =SUM(Enero!$L9,Enero!$M9) -> 11.22 | O9: =SUM(Enero!$N9, Enero!$H9, Enero!$I9, Enero!$J9) -> 73.635 | P9: =Enero!$O9/Enero!$F9 -> 4.909 | Q9: 8.2 | R9: =Enero!$F9*Enero!$Q9 -> 123 | S9: =Enero!$R9-Enero!$O9 -> 49.365 | T9: =((Enero!$Q9-Enero!$P9)/Enero!$P9) -> 0.6704013 | U9: =((Enero!$Q9-Enero!$P9)/Enero!$Q9) -> 0.40134146 | V9: Link
A10: Cinturon Gym | B10: 0.4 | C10: =Enero!$B10*2.2 -> 0.88 | D10: =Enero!$F10*Enero!$B10 -> 4 | E10: =PRODUCT(F10,C10) -> 8.8 | F10: 10 | G10: 2.81 | H10: =Enero!$F10*Enero!$G10 -> 28.1 | I10: =Enero!$H10*0.06 -> 1.686 | J10: =Enero!$H10*0.035 -> 0.9835 | K10: =SUM(Enero!$H10,Enero!$I10,Enero!$J10) -> 30.7695 | L10: =1.4*Enero!$E10 -> 12.32 | M10: =Enero!$E10*$E$31 -> 17.6 | N10: =SUM(Enero!$L10,Enero!$M10) -> 29.92 | O10: =SUM(Enero!$N10, Enero!$H10, Enero!$I10, Enero!$J10) -> 60.6895 | P10: =Enero!$O10/Enero!$F10 -> 6.06895 | Q10: 10.1 | R10: =Enero!$F10*Enero!$Q10 -> 101 | S10: =Enero!$R10-Enero!$O10 -> 40.3105 | T10: =((Enero!$Q10-Enero!$P10)/Enero!$P10) -> 0.6642088 | U10: =((Enero!$Q10-Enero!$P10)/Enero!$Q10) -> 0.39911386 | V10: Link
A11: Manga deportiva | B11: 0.1 | C11: =Enero!$B11*2.2 -> 0.22 | D11: =Enero!$F11*Enero!$B11 -> 0.8 | E11: =PRODUCT(F11,C11) -> 1.76 | F11: 8 | G11: 1.23 | H11: =Enero!$F11*Enero!$G11 -> 9.84 | I11: =Enero!$H11*0.06 -> 0.5904 | J11: =Enero!$H11*0.035 -> 0.3444 | K11: =SUM(Enero!$H11,Enero!$I11,Enero!$J11) -> 10.7748 | L11: =1.4*Enero!$E11 -> 2.464 | M11: =Enero!$E11*$E$31 -> 3.52 | N11: =SUM(Enero!$L11,Enero!$M11) -> 5.984 | O11: =SUM(Enero!$N11, Enero!$H11, Enero!$I11, Enero!$J11) -> 16.7588 | P11: =Enero!$O11/Enero!$F11 -> 2.09485 | Q11: 3.5 | R11: =Enero!$F11*Enero!$Q11 -> 28 | S11: =Enero!$R11-Enero!$O11 -> 11.2412 | T11: =((Enero!$Q11-Enero!$P11)/Enero!$P11) -> 0.67076402 | U11: =((Enero!$Q11-Enero!$P11)/Enero!$Q11) -> 0.40147143 | V11: Link
A12: Pantalones Gym Dama v2 | B12: 0.2 | C12: =Enero!$B12*2.2 -> 0.44 | D12: =Enero!$F12*Enero!$B12 -> 4 | E12: =PRODUCT(F12,C12) -> 8.8 | F12: 20 | G12: 4.91 | H12: =Enero!$F12*Enero!$G12 -> 98.2 | I12: =Enero!$H12*0.06 -> 5.892 | J12: =Enero!$H12*0.035 -> 3.437 | K12: =SUM(Enero!$H12,Enero!$I12,Enero!$J12) -> 107.529 | L12: =1.4*Enero!$E12 -> 12.32 | M12: =Enero!$E12*$E$31 -> 17.6 | N12: =SUM(Enero!$L12,Enero!$M12) -> 29.92 | O12: =SUM(Enero!$N12, Enero!$H12, Enero!$I12, Enero!$J12) -> 137.449 | P12: =Enero!$O12/Enero!$F12 -> 6.87245 | Q12: 11.5 | R12: =Enero!$F12*Enero!$Q12 -> 230 | S12: =Enero!$R12-Enero!$O12 -> 92.551 | T12: =((Enero!$Q12-Enero!$P12)/Enero!$P12) -> 0.67334793 | U12: =((Enero!$Q12-Enero!$P12)/Enero!$Q12) -> 0.40239565 | V12: Link
A13: Shorts Gymshark | B13: 0.2 | C13: =Enero!$B13*2.2 -> 0.44 | D13: =Enero!$F13*Enero!$B13 -> 2 | E13: =PRODUCT(F13,C13) -> 4.4 | F13: 10 | G13: 5.61 | H13: =Enero!$F13*Enero!$G13 -> 56.1 | I13: =Enero!$H13*0.06 -> 3.366 | J13: =Enero!$H13*0.035 -> 1.9635 | K13: =SUM(Enero!$H13,Enero!$I13,Enero!$J13) -> 61.4295 | L13: =1.4*Enero!$E13 -> 6.16 | M13: =Enero!$E13*$E$31 -> 8.8 | N13: =SUM(Enero!$L13,Enero!$M13) -> 14.96 | O13: =SUM(Enero!$N13, Enero!$H13, Enero!$I13, Enero!$J13) -> 76.3895 | P13: =Enero!$O13/Enero!$F13 -> 7.63895 | Q13: 12.8 | R13: =Enero!$F13*Enero!$Q13 -> 128 | S13: =Enero!$R13-Enero!$O13 -> 51.6105 | T13: =((Enero!$Q13-Enero!$P13)/Enero!$P13) -> 0.67562296 | U13: =((Enero!$Q13-Enero!$P13)/Enero!$Q13) -> 0.40320703 | V13: Link
A14: Tops deportivos | B14: 0.2 | C14: =Enero!$B14*2.2 -> 0.44 | D14: =Enero!$F14*Enero!$B14 -> 2.4 | E14: =PRODUCT(F14,C14) -> 5.28 | F14: 12 | G14: 3.91 | H14: =Enero!$F14*Enero!$G14 -> 46.92 | I14: =Enero!$H14*0.06 -> 2.8152 | J14: =Enero!$H14*0.035 -> 1.6422 | K14: =SUM(Enero!$H14,Enero!$I14,Enero!$J14) -> 51.3774 | L14: =1.4*Enero!$E14 -> 7.392 | M14: =Enero!$E14*$E$31 -> 10.56 | N14: =SUM(Enero!$L14,Enero!$M14) -> 17.952 | O14: =SUM(Enero!$N14, Enero!$H14, Enero!$I14, Enero!$J14) -> 69.3294 | P14: =Enero!$O14/Enero!$F14 -> 5.77745 | Q14: 9.6 | R14: =Enero!$F14*Enero!$Q14 -> 115.2 | S14: =Enero!$R14-Enero!$O14 -> 45.8706 | T14: =((Enero!$Q14-Enero!$P14)/Enero!$P14) -> 0.66163273 | U14: =((Enero!$Q14-Enero!$P14)/Enero!$Q14) -> 0.39818229 | V14: Link
A15: Straps | B15: 0.1 | C15: =Enero!$B15*2.2 -> 0.22 | D15: =Enero!$F15*Enero!$B15 -> 2 | E15: =PRODUCT(F15,C15) -> 4.4 | F15: 20 | G15: 1.75 | H15: =Enero!$F15*Enero!$G15 -> 35 | I15: =Enero!$H15*0.06 -> 2.1 | J15: =Enero!$H15*0.035 -> 1.225 | K15: =SUM(Enero!$H15,Enero!$I15,Enero!$J15) -> 38.325 | L15: =1.4*Enero!$E15 -> 6.16 | M15: =Enero!$E15*$E$31 -> 8.8 | N15: =SUM(Enero!$L15,Enero!$M15) -> 14.96 | O15: =SUM(Enero!$N15, Enero!$H15, Enero!$I15, Enero!$J15) -> 53.285 | P15: =Enero!$O15/Enero!$F15 -> 2.66425 | Q15: 6 | R15: =Enero!$F15*Enero!$Q15 -> 120 | S15: =Enero!$R15-Enero!$O15 -> 66.715 | T15: =((Enero!$Q15-Enero!$P15)/Enero!$P15) -> 1.2520409 | U15: =((Enero!$Q15-Enero!$P15)/Enero!$Q15) -> 0.55595833 | V15: Link
A16: Camisas de compresion | B16: 0.2 | C16: =Enero!$B16*2.2 -> 0.44 | D16: =Enero!$F16*Enero!$B16 -> 10 | E16: =PRODUCT(F16,C16) -> 22 | F16: 50 | G16: 1.8 | H16: =Enero!$F16*Enero!$G16 -> 90 | I16: =Enero!$H16*0.06 -> 5.4 | J16: =Enero!$H16*0.035 -> 3.15 | K16: =SUM(Enero!$H16,Enero!$I16,Enero!$J16) -> 98.55 | L16: =1.4*Enero!$E16 -> 30.8 | M16: =Enero!$E16*$E$31 -> 44 | N16: =SUM(Enero!$L16,Enero!$M16) -> 74.8 | O16: =SUM(Enero!$N16, Enero!$H16, Enero!$I16, Enero!$J16) -> 173.35 | P16: =Enero!$O16/Enero!$F16 -> 3.467 | Q16: 6 | R16: =Enero!$F16*Enero!$Q16 -> 300 | S16: =Enero!$R16-Enero!$O16 -> 126.65 | T16: =((Enero!$Q16-Enero!$P16)/Enero!$P16) -> 0.73060283 | U16: =((Enero!$Q16-Enero!$P16)/Enero!$Q16) -> 0.42216667 | V16: Link
A17: Total | B17: =SUM(B8:B16) -> 2.03 | C17: =SUM(C8:C16) -> 4.466 | D17: 35 | E17: =SUM(E8:E16) -> 84.392 | F17: =SUM(F8:F16) -> 167 | G17: =SUM(G8:G16) -> 31.01 | H17: =SUM(H8:H16) -> 535.34 | I17: =Enero!$H17*0.06 -> 32.1204 | J17: =Enero!$H17*0.035 -> 18.7369 | K17: =SUM(Enero!$H17,Enero!$I17,Enero!$J17) -> 586.1973 | L17: =SUM(L8:L16) -> 118.1488 | M17: =SUM(M8:M16) -> 168.784 | N17: =SUM(N8:N16) -> 286.9328 | O17: =SUM(O8:O16) -> 873.1301 | P17: =SUM(P8:P16) -> 49.14035 | Q17: =SUM(Q8:Q16) -> 83.7 | R17: =SUM(R8:R16) -> 1497.2 | S17: =SUM(S8:S16) -> 624.0699
A29: Concepto | B29: Monto (USD)
A30: Ingresos totales por ventas | B30: =R17 -> 1497.2 | D30: COSTOS x libra | E30: Cantidad (Dólares)
D31: Envío de productos (USA-NIC) | E31: 2
A32: Costos de operación | D32: Envío de productos (CHN-USA) | E32: 1. 4
A33: - Costo total de productos | B33: =SUM(K8:K16) -> 586.1973
A34: - Costo total de envío | B34: =SUM(N8:N15) -> 212.1328
A35: Gastos operativos | B35: 300
A36: Costo total de la operación | B36: =SUM(B33:B35) -> 1098.3301
A38: Utilidad bruta | B38: =B30-B33-B34 -> 698.8699 | H38: gastos operativos | I38: valor
A39: Utilidad neta | B39: =B38-B35 -> 398.8699 | H39: deuda | I39: 200
H40: gasolina | I40: 50
A41: Márgenes | H41: otros | I41: 50
A42: - Margen bruto sobre ingresos (%) | B42: =B38/B30 -> 0.4667846
A43: - Margen neto sobre ingresos (%) | B43: =B39/B30 -> 0.26641057
A44: - Margen neto sobre costos totales (%) | B44: =B39/B36 -> 0.36316031

Sheet Febrero
G6: Cambio oficial dólar a códoba | H6: 36.62
B7: TABLA DE COSTOS Febrero
B8: Producto | C8: Peso del producto en Kg | D8: Peso Unitario (libras) | E8: Peso total en Kg | F8: Peso total (libras) | G8: Cantidad | H8: Costo Unitario ($) | I8: Costo Total | J8: comisión sobre transacción | K8: costo de envío interno en china | L8: Costo total total al almacen | M8: Costo Envío China-USA | N8: Costo Envío USA-NIC ($) | O8: Costo envío Total ($) | P8: Costo Total Lote ($) | Q8: Costo Unitario NIC | R8: Precio de venta | S8: Ingreso total por producto | T8: utilidad por producto | U8: margen sobre costros por producto | V8: margen sobre ventas por productos | W8: Links
B9: Camisas de compresion | C9: 0.2 | D9: =Febrero!$C9*2.2 -> 0.44 | E9: =Febrero!$G9*Febrero!$C9 -> 10 | F9: =Febrero!$E9*2.2 -> 22 | G9: 50 | H9: 1.81 | I9: =Febrero!$G9*Febrero!$H9 -> 90.5 | J9: =Febrero!$I9*0.0295 -> 2.66975 | K9: =Febrero!$I9*0.03 -> 2.715 | L9: =SUM(Febrero!$I9,Febrero!$J9,Febrero!$K9) -> 95.88475 | M9: =1.4*Febrero!$F9 -> 30.8 | N9: =Febrero!$F9*$E$31 -> 55 | O9: =SUM(Febrero!$M9,Febrero!$N9) -> 85.8 | P9: =SUM(Febrero!$O9, Febrero!$I9, Febrero!$J9, Febrero!$K9) -> 181.68475 | Q9: =Febrero!$P9/Febrero!$G9 -> 3.633695 | R9: 6.79 | S9: =Febrero!$G9*Febrero!$R9 -> 339.5 | T9: =Febrero!$S9-Febrero!$P9 -> 157.81525 | U9: =((Febrero!$R9-Febrero!$Q9)/Febrero!$Q9) -> 0.86862133 | V9: =((Febrero!$R9-Febrero!$Q9)/Febrero!$R9) -> 0.4648461 | W9: si
B10: Chaleco de lana | C10: 0.5 | D10: =Febrero!$C10*2.2 -> 1.1 | E10: =Febrero!$G10*Febrero!$C10 -> 25 | F10: =Febrero!$E10*2.2 -> 55 | G10: 50 | H10: 4.95 | I10: =Febrero!$G10*Febrero!$H10 -> 247.5 | J10: =Febrero!$I10*0.0295 -> 7.30125 | K10: =Febrero!$I10*0.03 -> 7.425 | L10: =SUM(Febrero!$I10,Febrero!$J10,Febrero!$K10) -> 262.22625 | M10: =1.4*Febrero!$F10 -> 77 | N10: =Febrero!$F10*$E$31 -> 137.5 | O10: =SUM(Febrero!$M10,Febrero!$N10) -> 214.5 | P10: =SUM(Febrero!$O10, Febrero!$I10, Febrero!$J10, Febrero!$K10) -> 476.72625 | Q10: =Febrero!$P10/Febrero!$G10 -> 9.534525 | R10: 12.26 | S10: =Febrero!$G10*Febrero!$R10 -> 613 | T10: =Febrero!$S10-Febrero!$P10 -> 136.27375 | U10: =((Febrero!$R10-Febrero!$Q10)/Febrero!$Q10) -> 0.28585325 | V10: =((Febrero!$R10-Febrero!$Q10)/Febrero!$R10) -> 0.22230628 | W10: si
B11: Camisas de compresion manga larga | C11: 0.2 | D11: =Febrero!$C11*2.2 -> 0.44 | E11: =Febrero!$G11*Febrero!$C11 -> 5 | F11: =PRODUCT(G11,D11) -> 11 | G11: 25 | H11: 1.53 | I11: =Febrero!$G11*Febrero!$H11 -> 38.25 | J11: =Febrero!$I11*0.0295 -> 1.128375 | K11: =Febrero!$I11*0.03 -> 1.1475 | L11: =SUM(Febrero!$I11,Febrero!$J11,Febrero!$K11) -> 40.525875 | M11: =1.4*Febrero!$F11 -> 15.4 | N11: =Febrero!$F11*$E$31 -> 27.5 | O11: =SUM(Febrero!$M11,Febrero!$N11) -> 42.9 | P11: =SUM(Febrero!$O11, Febrero!$I11, Febrero!$J11, Febrero!$K11) -> 83.425875 | Q11: =Febrero!$P11/Febrero!$G11 -> 3.337035 | R11: 8.15 | S11: =Febrero!$G11*Febrero!$R11 -> 203.75 | T11: =Febrero!$S11-Febrero!$P11 -> 120.32412 | U11: =((Febrero!$R11-Febrero!$Q11)/Febrero!$Q11) -> 1.4422878 | V11: =((Febrero!$R11-Febrero!$Q11)/Febrero!$R11) -> 0.59054785 | W11: si
B12: Camisas de compresion sin mangas | C12: 0.2 | D12: =Febrero!$C12*2.2 -> 0.44 | E12: =Febrero!$G12*Febrero!$C12 -> 5 | F12: =PRODUCT(G12,D12) -> 11 | G12: 25 | H12: 1.95 | I12: =Febrero!$G12*Febrero!$H12 -> 48.75 | J12: =Febrero!$I12*0.0295 -> 1.438125 | K12: =Febrero!$I12*0.03 -> 1.4625 | L12: =SUM(Febrero!$I12,Febrero!$J12,Febrero!$K12) -> 51.650625 | M12: =1.4*Febrero!$F12 -> 15.4 | N12: =Febrero!$F12*$E$31 -> 27.5 | O12: =SUM(Febrero!$M12,Febrero!$N12) -> 42.9 | P12: =SUM(Febrero!$O12, Febrero!$I12, Febrero!$J12, Febrero!$K12) -> 94.550625 | Q12: =Febrero!$P12/Febrero!$G12 -> 3.782025 | R12: 8.15 | S12: =Febrero!$G12*Febrero!$R12 -> 203.75 | T12: =Febrero!$S12-Febrero!$P12 -> 109.19938 | U12: =((Febrero!$R12-Febrero!$Q12)/Febrero!$Q12) -> 1.1549302 | V12: =((Febrero!$R12-Febrero!$Q12)/Febrero!$R12) -> 0.53594785 | W12: si
B13: Soporte de laptop | C13: 0.25 | D13: =Febrero!$C13*2.2 -> 0.55 | E13: =Febrero!$G13*Febrero!$C13 -> 2.5 | F13: =PRODUCT(G13,D13) -> 5.5 | G13: 10 | H13: 1.4 | I13: =Febrero!$G13*Febrero!$H13 -> 14 | J13: =Febrero!$I13*0.0295 -> 0.413 | K13: =Febrero!$I13*0.03 -> 0.42 | L13: =SUM(Febrero!$I13,Febrero!$J13,Febrero!$K13) -> 14.833 | M13: =1.4*Febrero!$F13 -> 7.7 | N13: =Febrero!$F13*$E$31 -> 13.75 | O13: =SUM(Febrero!$M13,Febrero!$N13) -> 21.45 | P13: =SUM(Febrero!$O13, Febrero!$I13, Febrero!$J13, Febrero!$K13) -> 36.283 | Q13: =Febrero!$P13/Febrero!$G13 -> 3.6283 | R13: 6 | S13: =Febrero!$G13*Febrero!$R13 -> 60 | T13: =Febrero!$S13-Febrero!$P13 -> 23.717 | U13: =((Febrero!$R13-Febrero!$Q13)/Febrero!$Q13) -> 0.65366701 | V13: =((Febrero!$R13-Febrero!$Q13)/Febrero!$R13) -> 0.39528333 | W13: Si
B14: Mochila antirobo | C14: 0.2 | D14: =Febrero!$C14*2.2 -> 0.44 | E14: =Febrero!$G14*Febrero!$C14 -> 2.4 | F14: =PRODUCT(G14,D14) -> 5.28 | G14: 12 | H14: 1.7 | I14: =Febrero!$G14*Febrero!$H14 -> 20.4 | J14: =Febrero!$I14*0.0295 -> 0.6018 | K14: =Febrero!$I14*0.03 -> 0.612 | L14: =SUM(Febrero!$I14,Febrero!$J14,Febrero!$K14) -> 21.6138 | M14: =1.4*Febrero!$F14 -> 7.392 | N14: =Febrero!$F14*$E$31 -> 13.2 | O14: =SUM(Febrero!$M14,Febrero!$N14) -> 20.592 | P14: =SUM(Febrero!$O14, Febrero!$I14, Febrero!$J14, Febrero!$K14) -> 42.2058 | Q14: =Febrero!$P14/Febrero!$G14 -> 3.51715 | R14: 6 | S14: =Febrero!$G14*Febrero!$R14 -> 72 | T14: =Febrero!$S14-Febrero!$P14 -> 29.7942 | U14: =((Febrero!$R14-Febrero!$Q14)/Febrero!$Q14) -> 0.70592667 | V14: =((Febrero!$R14-Febrero!$Q14)/Febrero!$R14) -> 0.41380833 | W14: si
B15: Jogger estilo 1 | C15: 0.2 | D15: =Febrero!$C15*2.2 -> 0.44 | E15: =Febrero!$G15*Febrero!$C15 -> 2 | F15: =PRODUCT(G15,D15) -> 4.4 | G15: 10 | H15: 4.38 | I15: =Febrero!$G15*Febrero!$H15 -> 43.8 | J15: =Febrero!$I15*0.0295 -> 1.2921 | K15: =Febrero!$I15*0.03 -> 1.314 | L15: =SUM(Febrero!$I15,Febrero!$J15,Febrero!$K15) -> 46.4061 | M15: =1.4*Febrero!$F15 -> 6.16 | N15: =Febrero!$F15*$E$31 -> 11 | O15: =SUM(Febrero!$M15,Febrero!$N15) -> 17.16 | P15: =SUM(Febrero!$O15, Febrero!$I15, Febrero!$J15, Febrero!$K15) -> 63.5661 | Q15: =Febrero!$P15/Febrero!$G15 -> 6.35661 | R15: 10.88 | S15: =Febrero!$G15*Febrero!$R15 -> 108.8 | T15: =Febrero!$S15-Febrero!$P15 -> 45.2339 | U15: =((Febrero!$R15-Febrero!$Q15)/Febrero!$Q15) -> 0.71160414 | V15: =((Febrero!$R15-Febrero!$Q15)/Febrero!$R15) -> 0.41575276 | W15: Si
B16: - | C16: 0 | D16: =Febrero!$C16*2.2 -> 0 | E16: =Febrero!$G16*Febrero!$C16 -> 0 | F16: =PRODUCT(G16,D16) -> 0 | G16: 0 | H16: 0 | I16: =Febrero!$G16*Febrero!$H16 -> 0 | J16: =Febrero!$I16*0.0295 -> 0 | K16: =Febrero!$I16*0.03 -> 0 | L16: =SUM(Febrero!$I16,Febrero!$J16,Febrero!$K16) -> 0 | M16: =1.4*Febrero!$F16 -> 0 | N16: =Febrero!$F16*$E$31 -> 0 | O16: =SUM(Febrero!$M16,Febrero!$N16) -> 0 | P16: =SUM(Febrero!$O16, Febrero!$I16, Febrero!$J16, Febrero!$K16) -> 0 | Q16: 0 | R16: 0 | S16: =Febrero!$G16*Febrero!$R16 -> 0 | T16: =Febrero!$S16-Febrero!$P16 -> 0 | U16: 0 | V16: 0
B17: - | C17: 0 | D17: =Febrero!$C17*2.2 -> 0 | E17: =Febrero!$G17*Febrero!$C17 -> 0 | F17: =PRODUCT(G17,D17) -> 0 | G17: 0 | H17: 0 | I17: =Febrero!$G17*Febrero!$H17 -> 0 | J17: =Febrero!$I17*0.0295 -> 0 | K17: =Febrero!$I17*0.03 -> 0 | L17: =SUM(Febrero!$I17,Febrero!$J17,Febrero!$K17) -> 0 | M17: =1.4*Febrero!$F17 -> 0 | N17: =Febrero!$F17*$E$31 -> 0 | O17: =SUM(Febrero!$M17,Febrero!$N17) -> 0 | P17: =SUM(Febrero!$O17, Febrero!$I17, Febrero!$J17, Febrero!$K17) -> 0 | Q17: 0 | R17: 0 | S17: =Febrero!$G17*Febrero!$R17 -> 0 | T17: =Febrero!$S17-Febrero!$P17 -> 0 | U17: 0 | V17: 0
B18: Total | C18: =SUM(C9:C17) -> 1.75 | D18: =SUM(D9:D17) -> 3.85 | E18: 35 | F18: =SUM(F9:F17) -> 114.18 | G18: =SUM(G9:G17) -> 182 | H18: =SUM(H9:H17) -> 17.72 | I18: =SUM(I9:I17) -> 503.2 | J18: =Febrero!$I18*0.0295 -> 14.8444 | K18: =Febrero!$I18*0.03 -> 15.096 | L18: =SUM(Febrero!$I18,Febrero!$J18,Febrero!$K18) -> 533.1404 | M18: =SUM(M9:M17) -> 159.852 | N18: =SUM(N9:N17) -> 285.45 | O18: =SUM(O9:O17) -> 445.302 | P18: =SUM(P9:P17) -> 978.4424 | Q18: =SUM(Q9:Q17) -> 33.78934 | R18: =SUM(R9:R17) -> 58.23 | S18: =SUM(S9:S17) -> 1600.8 | T18: =SUM(T9:T17) -> 622.3576
A29: Concepto | B29: Monto (USD)
A30: Ingresos totales por ventas | B30: =R18 -> 58.23 | D30: COSTOS x libra | E30: Cantidad (Dólares)
D31: Envío de productos (USA-NIC) | E31: 2.5
A32: Costos de operación | D32: Envío de productos (CHN-USA) | E32: 1. 4
A33: - Costo total de productos | B33: =SUM(K8:K15) -> 15.096
A34: - Costo total de envío | B34: =SUM(N8:N15) -> 285.45
A35: - Gastos de marketing/publicidad | B35: =SUM(O17:O20) -> 445.302
A36: Costo total de la operación | B36: =SUM(B33:B35) -> 745.848
A38: Utilidad bruta | B38: =B30-B33-B34 -> -242.316
A39: Utilidad neta | B39: =B38-B35 -> -687.618
A41: Márgenes
A42: - Margen bruto sobre ingresos (%) | B42: =B38/B30 -> -4.1613601
A43: - Margen neto sobre ingresos (%) | B43: =B39/B30 -> -11.808655
A44: - Margen neto sobre costos totales (%) | B44: =B39/B36 -> -0.92192779

Sheet Abril-Mayo
F5: Cambio oficial dólar a códoba | G5: 36.62
A6: TABLA DE COSTOS
A7: Producto | B7: Peso del producto en Kg | C7: Peso Unitario (libras) | D7: Peso total en Kg | E7: Peso total (libras) | F7: Cantidad | G7: Costo Unitario ($) | H7: Costo Total | I7: comisión sobre transacción | J7: costo de envío interno en china | K7: Costo total total al almacen | L7: Costo Envío China-USA | M7: Costo Envío USA-NIC ($) | N7: Costo envío Total ($) | O7: Costo Total Lote ($) | P7: Costo Unitario NIC | Q7: Precio de venta | R7: Ingreso total por producto | S7: utilidad por producto | T7: margen sobre costros por producto | U7: margen sobre ventas por productos | V7: Links | W7: Origen
A8: Camisa de compresion | B8: 0.2 | C8: ='Abril-Mayo'!$B8*2.2 -> 0.44 | D8: ='Abril-Mayo'!$F8*'Abril-Mayo'!$B8 -> 10 | E8: ='Abril-Mayo'!$D8*2.2 -> 22 | F8: 50 | G8: 1.88 | H8: ='Abril-Mayo'!$F8*'Abril-Mayo'!$G8+20 -> 114 | I8: ='Abril-Mayo'!$H8*0.06 -> 6.84 | J8: 1.77 | K8: =SUM('Abril-Mayo'!$H8,'Abril-Mayo'!$I8,'Abril-Mayo'!$J8) -> 122.61 | L8: =1.4*'Abril-Mayo'!$E8 -> 30.8 | M8: ='Abril-Mayo'!$E8*$E$29 -> 44 | N8: =SUM('Abril-Mayo'!$L8,'Abril-Mayo'!$M8) -> 74.8 | O8: =SUM('Abril-Mayo'!$N8, 'Abril-Mayo'!$H8, 'Abril-Mayo'!$I8, 'Abril-Mayo'!$J8) -> 197.41 | P8: ='Abril-Mayo'!$O8/'Abril-Mayo'!$F8 -> 3.9482 | Q8: 8.64 | R8: ='Abril-Mayo'!$F8*'Abril-Mayo'!$Q8 -> 432 | S8: ='Abril-Mayo'!$R8-'Abril-Mayo'!$O8 -> 234.59 | T8: =(('Abril-Mayo'!$Q8-'Abril-Mayo'!$P8)/'Abril-Mayo'!$P8) -> 1.188339 | U8: =(('Abril-Mayo'!$Q8-'Abril-Mayo'!$P8)/'Abril-Mayo'!$Q8) -> 0.54303241 | V8: link | W8: 1688
A9: Flare leggins | B9: 0.5 | C9: ='Abril-Mayo'!$B9*2.2 -> 1.1 | D9: ='Abril-Mayo'!$F9*'Abril-Mayo'!$B9 -> 15 | E9: ='Abril-Mayo'!$D9*2.2 -> 33 | F9: 30 | G9: 4.89 | H9: ='Abril-Mayo'!$F9*'Abril-Mayo'!$G9+20 -> 166.7 | I9: ='Abril-Mayo'!$H9*0.06 -> 10.002 | J9: 6.62 | K9: =SUM('Abril-Mayo'!$H9,'Abril-Mayo'!$I9,'Abril-Mayo'!$J9) -> 183.322 | L9: =1.4*'Abril-Mayo'!$E9 -> 46.2 | M9: ='Abril-Mayo'!$E9*$E$29 -> 66 | N9: =SUM('Abril-Mayo'!$L9,'Abril-Mayo'!$M9) -> 112.2 | O9: =SUM('Abril-Mayo'!$N9, 'Abril-Mayo'!$H9, 'Abril-Mayo'!$I9, 'Abril-Mayo'!$J9) -> 295.522 | P9: ='Abril-Mayo'!$O9/'Abril-Mayo'!$F9 -> 9.8507333 | Q9: 15 | R9: ='Abril-Mayo'!$F9*'Abril-Mayo'!$Q9 -> 450 | S9: ='Abril-Mayo'!$R9-'Abril-Mayo'!$O9 -> 154.478 | T9: =(('Abril-Mayo'!$Q9-'Abril-Mayo'!$P9)/'Abril-Mayo'!$P9) -> 0.52272927 | U9: =(('Abril-Mayo'!$Q9-'Abril-Mayo'!$P9)/'Abril-Mayo'!$Q9) -> 0.34328444 | V9: link | W9: 1688
A10: Mono deportivo | B10: 0.3 | C10: ='Abril-Mayo'!$B10*2.2 -> 0.66 | D10: ='Abril-Mayo'!$F10*'Abril-Mayo'!$B10 -> 1.2 | E10: ='Abril-Mayo'!$D10*2.2 -> 2.64 | F10: 4 | G10: 4.71 | H10: ='Abril-Mayo'!$F10*'Abril-Mayo'!$G10+20 -> 38.84 | I10: ='Abril-Mayo'!$H10*0.06 -> 2.3304 | J10: 1.1 | K10: =SUM('Abril-Mayo'!$H10,'Abril-Mayo'!$I10,'Abril-Mayo'!$J10) -> 42.2704 | L10: =1.4*'Abril-Mayo'!$E10 -> 3.696 | M10: ='Abril-Mayo'!$E10*$E$29 -> 5.28 | N10: =SUM('Abril-Mayo'!$L10,'Abril-Mayo'!$M10) -> 8.976 | O10: =SUM('Abril-Mayo'!$N10, 'Abril-Mayo'!$H10, 'Abril-Mayo'!$I10, 'Abril-Mayo'!$J10) -> 51.2464 | P10: ='Abril-Mayo'!$O10/'Abril-Mayo'!$F10 -> 12.8116 | Q10: 20.01 | R10: ='Abril-Mayo'!$F10*'Abril-Mayo'!$Q10 -> 80.04 | S10: ='Abril-Mayo'!$R10-'Abril-Mayo'!$O10 -> 28.7936 | T10: =(('Abril-Mayo'!$Q10-'Abril-Mayo'!$P10)/'Abril-Mayo'!$P10) -> 0.56186581 | U10: =(('Abril-Mayo'!$Q10-'Abril-Mayo'!$P10)/'Abril-Mayo'!$Q10) -> 0.35974013 | V10: link | W10: 1688
A11: Camisa de compresion sin manga | B11: 0.2 | C11: ='Abril-Mayo'!$B11*2.2 -> 0.44 | D11: ='Abril-Mayo'!$F11*'Abril-Mayo'!$B11 -> 4 | E11: ='Abril-Mayo'!$D11*2.2 -> 8.8 | F11: 20 | G11: 1.59 | H11: ='Abril-Mayo'!$F11*'Abril-Mayo'!$G11+20 -> 51.8 | I11: ='Abril-Mayo'!$H11*0.06 -> 3.108 | J11: 2.94 | K11: =SUM('Abril-Mayo'!$H11,'Abril-Mayo'!$I11,'Abril-Mayo'!$J11) -> 57.848 | L11: =1.4*'Abril-Mayo'!$E11 -> 12.32 | M11: ='Abril-Mayo'!$E11*$E$29 -> 17.6 | N11: =SUM('Abril-Mayo'!$L11,'Abril-Mayo'!$M11) -> 29.92 | O11: =SUM('Abril-Mayo'!$N11, 'Abril-Mayo'!$H11, 'Abril-Mayo'!$I11, 'Abril-Mayo'!$J11) -> 87.768 | P11: ='Abril-Mayo'!$O11/'Abril-Mayo'!$F11 -> 4.3884 | Q11: 8.64 | R11: ='Abril-Mayo'!$F11*'Abril-Mayo'!$Q11 -> 172.8 | S11: ='Abril-Mayo'!$R11-'Abril-Mayo'!$O11 -> 85.032 | T11: =(('Abril-Mayo'!$Q11-'Abril-Mayo'!$P11)/'Abril-Mayo'!$P11) -> 0.96882691 | U11: =(('Abril-Mayo'!$Q11-'Abril-Mayo'!$P11)/'Abril-Mayo'!$Q11) -> 0.49208333 | W11: 1688
A12: Shorts YOUNGLA | B12: 0.2 | C12: ='Abril-Mayo'!$B12*2.2 -> 0.44 | D12: ='Abril-Mayo'!$F12*'Abril-Mayo'!$B12 -> 3.2 | E12: ='Abril-Mayo'!$D12*2.2 -> 7.04 | F12: 16 | G12: 3.83 | H12: ='Abril-Mayo'!$F12*'Abril-Mayo'!$G12+20 -> 81.28 | I12: ='Abril-Mayo'!$H12*0.06 -> 4.8768 | J12: 6.33 | K12: =SUM('Abril-Mayo'!$H12,'Abril-Mayo'!$I12,'Abril-Mayo'!$J12) -> 92.4868 | L12: =1.4*'Abril-Mayo'!$E12 -> 9.856 | M12: ='Abril-Mayo'!$E12*$E$29 -> 14.08 | N12: =SUM('Abril-Mayo'!$L12,'Abril-Mayo'!$M12) -> 23.936 | O12: =SUM('Abril-Mayo'!$N12, 'Abril-Mayo'!$H12, 'Abril-Mayo'!$I12, 'Abril-Mayo'!$J12) -> 116.4228 | P12: ='Abril-Mayo'!$O12/'Abril-Mayo'!$F12 -> 7.276425 | Q12: 12.16 | R12: ='Abril-Mayo'!$F12*'Abril-Mayo'!$Q12 -> 194.56 | S12: ='Abril-Mayo'!$R12-'Abril-Mayo'!$O12 -> 78.1372 | T12: =(('Abril-Mayo'!$Q12-'Abril-Mayo'!$P12)/'Abril-Mayo'!$P12) -> 0.67115032 | U12: =(('Abril-Mayo'!$Q12-'Abril-Mayo'!$P12)/'Abril-Mayo'!$Q12) -> 0.40160979 | V12: Link | W12: 1688
A13: enterizo | B13: 0.3 | C13: ='Abril-Mayo'!$B13*2.2 -> 0.66 | D13: ='Abril-Mayo'!$F13*'Abril-Mayo'!$B13 -> 9 | E13: ='Abril-Mayo'!$D13*2.2 -> 19.8 | F13: 30 | G13: 3.06 | H13: ='Abril-Mayo'!$F13*'Abril-Mayo'!$G13+20 -> 111.8 | I13: ='Abril-Mayo'!$H13*0.06 -> 6.708 | J13: 2.94 | K13: =SUM('Abril-Mayo'!$H13,'Abril-Mayo'!$I13,'Abril-Mayo'!$J13) -> 121.448 | L13: =1.4*'Abril-Mayo'!$E13 -> 27.72 | M13: ='Abril-Mayo'!$E13*$E$29 -> 39.6 | N13: =SUM('Abril-Mayo'!$L13,'Abril-Mayo'!$M13) -> 67.32 | O13: =SUM('Abril-Mayo'!$N13, 'Abril-Mayo'!$H13, 'Abril-Mayo'!$I13, 'Abril-Mayo'!$J13) -> 188.768 | P13: ='Abril-Mayo'!$O13/'Abril-Mayo'!$F13 -> 6.2922667 | Q13: 12.16 | R13: ='Abril-Mayo'!$F13*'Abril-Mayo'!$Q13 -> 364.8 | S13: ='Abril-Mayo'!$R13-'Abril-Mayo'!$O13 -> 176.032 | T13: =(('Abril-Mayo'!$Q13-'Abril-Mayo'!$P13)/'Abril-Mayo'!$P13) -> 0.93253094 | U13: =(('Abril-Mayo'!$Q13-'Abril-Mayo'!$P13)/'Abril-Mayo'!$Q13) -> 0.48254386 | V13: Link | W13: 1688
A14: Headphones | I14: ='Abril-Mayo'!$H14*0.06 -> 0
A15: shorts falda mujer | B15: 0.1 | C15: ='Abril-Mayo'!$B15*2.2 -> 0.22 | D15: ='Abril-Mayo'!$F15*'Abril-Mayo'!$B15 -> 2 | E15: ='Abril-Mayo'!$D15*2.2 -> 4.4 | F15: 20 | G15: 1.55 | H15: ='Abril-Mayo'!$F15*'Abril-Mayo'!$G15+20 -> 51 | I15: ='Abril-Mayo'!$H15*0.06 -> 3.06 | J15: 2.95 | K15: =SUM('Abril-Mayo'!$H15,'Abril-Mayo'!$I15,'Abril-Mayo'!$J15) -> 57.01 | L15: =1.4*'Abril-Mayo'!$E15 -> 6.16 | M15: ='Abril-Mayo'!$E15*$E$29 -> 8.8 | N15: =SUM('Abril-Mayo'!$L15,'Abril-Mayo'!$M15) -> 14.96 | O15: =SUM('Abril-Mayo'!$N15, 'Abril-Mayo'!$H15, 'Abril-Mayo'!$I15, 'Abril-Mayo'!$J15) -> 71.97 | P15: ='Abril-Mayo'!$O15/'Abril-Mayo'!$F15 -> 3.5985 | Q15: 10.81 | R15: ='Abril-Mayo'!$F15*'Abril-Mayo'!$Q15 -> 216.2 | S15: ='Abril-Mayo'!$R15-'Abril-Mayo'!$O15 -> 144.23 | T15: =(('Abril-Mayo'!$Q15-'Abril-Mayo'!$P15)/'Abril-Mayo'!$P15) -> 2.0040295 | U15: =(('Abril-Mayo'!$Q15-'Abril-Mayo'!$P15)/'Abril-Mayo'!$Q15) -> 0.66711378 | V15: Link | W15: 1688
A16: Camisa de compresion manga larga | B16: 0.2 | C16: ='Abril-Mayo'!$B16*2.2 -> 0.44 | D16: ='Abril-Mayo'!$F16*'Abril-Mayo'!$B16 -> 5 | E16: ='Abril-Mayo'!$D16*2.2 -> 11 | F16: 25 | G16: 2.03 | H16: ='Abril-Mayo'!$F16*'Abril-Mayo'!$G16+20 -> 70.75 | I16: ='Abril-Mayo'!$H16*0.06 -> 4.245 | J16: 2.94 | K16: =SUM('Abril-Mayo'!$H16,'Abril-Mayo'!$I16,'Abril-Mayo'!$J16) -> 77.935 | L16: =1.4*'Abril-Mayo'!$E16 -> 15.4 | M16: ='Abril-Mayo'!$E16*$E$29 -> 22 | N16: =SUM('Abril-Mayo'!$L16,'Abril-Mayo'!$M16) -> 37.4 | O16: =SUM('Abril-Mayo'!$N16, 'Abril-Mayo'!$H16, 'Abril-Mayo'!$I16, 'Abril-Mayo'!$J16) -> 115.335 | P16: ='Abril-Mayo'!$O16/'Abril-Mayo'!$F16 -> 4.6134 | Q16: 9.45 | R16: ='Abril-Mayo'!$F16*'Abril-Mayo'!$Q16 -> 236.25 | S16: ='Abril-Mayo'!$R16-'Abril-Mayo'!$O16 -> 120.915 | T16: =(('Abril-Mayo'!$Q16-'Abril-Mayo'!$P16)/'Abril-Mayo'!$P16) -> 1.0483808 | U16: =(('Abril-Mayo'!$Q16-'Abril-Mayo'!$P16)/'Abril-Mayo'!$Q16) -> 0.51180952 | W16: 1689
A18: Total | B18: =SUM(B8:B16) -> 2 | C18: ='Abril-Mayo'!$B18*2.2 -> 4.4 | D18: =SUM(D8:D16) -> 49.4 | E18: =SUM(E8:E16) -> 108.68 | F18: =SUM(F8:F16) -> 195 | G18: =SUM(G8:G16) -> 23.54 | H18: =SUM(H8:H16) -> 686.17 | I18: =SUM(H18,J18)*0.06 -> 42.8256 | J18: =SUM(J8:J17) -> 27.59 | K18: =SUM(K8:K17) -> 754.9302 | L18: =SUM(L8:L16) -> 152.152 | M18: =SUM(M8:M16) -> 217.36 | N18: =SUM(N8:N16) -> 369.512 | O18: =SUM(O8:O16) -> 1124.4422 | P18: =SUM(P8:P16) -> 52.779525 | Q18: =SUM(Q8:Q16) -> 96.87 | R18: =SUM(R8:R16) -> 2146.65 | S18: =SUM(S8:S16) -> 1022.2078
A27: Concepto | B27: Monto (USD)
A28: Ingresos totales por ventas | B28: =R18 -> 2146.65 | D28: COSTOS x libra | E28: Cantidad (Dólares)
D29: Envío de productos (USA-NIC) | E29: 2
A30: Costos de operación | D30: Envío de productos (CHN-USA) | E30: 1. 4
A31: - Costo total de productos | B31: =SUM(K8:K16) -> 754.9302
A32: - Costo total de envío | B32: =SUM(N8:N16) -> 369.512
A33: - Gastos de marketing/publicidad | B33: 400
A34: Costo total de la operación | B34: =SUM(B31:B32) -> 1124.4422
A36: Utilidad bruta | B36: =B28-B31-B32 -> 1022.2078
A37: Utilidad neta | B37: =B36-B33 -> 622.2078
A39: Márgenes
A40: - Margen bruto sobre ingresos (%) | B40: =B36/B28 -> 0.47618745
A41: - Margen neto sobre ingresos (%) | B41: =B37/B28 -> 0.2898506
A42: - Margen neto sobre costos totales (%) | B42: =B37/B34 -> 0.55334796

Sheet Junio-Julio
F5: Cambio oficial dólar a códoba | G5: 36.62
A6: TABLA DE COSTOS
A7: Producto | B7: Peso del producto en Kg | C7: Peso Unitario (libras) | D7: Peso total en Kg | E7: Peso total (libras) | F7: Cantidad | G7: Costo Unitario ($) | H7: Costo Total | I7: comisión sobre transacción | J7: costo de envío interno en china | K7: Costo total total al almacen | L7: Costo Envío China-USA | M7: Costo Envío USA-NIC ($) | N7: Costo envío Total ($) | O7: Costo Total Lote ($) | P7: Costo Unitario NIC | Q7: Precio de venta | R7: Ingreso total por producto | S7: utilidad por producto | T7: margen sobre costros por producto | U7: margen sobre ventas por productos | V7: Links | W7: Origen
A8: Camisa de compresion | B8: 0.2 | C8: ='Junio-Julio'!$B8*2.2 -> 0.44 | D8: ='Junio-Julio'!$F8*'Junio-Julio'!$B8 -> 10 | E8: ='Junio-Julio'!$D8*2.2 -> 22 | F8: 50 | G8: 1.86 | H8: ='Junio-Julio'!$F8*'Junio-Julio'!$G8 -> 93 | I8: ='Junio-Julio'!$H8*0.05 -> 4.65 | J8: ='Junio-Julio'!$H8*0.05 -> 4.65 | K8: =SUM('Junio-Julio'!$H8,'Junio-Julio'!$I8,'Junio-Julio'!$J8) -> 102.3 | L8: =1.4*'Junio-Julio'!$E8 -> 30.8 | M8: ='Junio-Julio'!$E8*$E$26 -> 55 | N8: =SUM('Junio-Julio'!$L8,'Junio-Julio'!$M8) -> 85.8 | O8: =SUM('Junio-Julio'!$N8, 'Junio-Julio'!$H8, 'Junio-Julio'!$I8, 'Junio-Julio'!$J8) -> 188.1 | P8: ='Junio-Julio'!$O8/'Junio-Julio'!$F8 -> 3.762 | Q8: 8.15 | R8: ='Junio-Julio'!$F8*'Junio-Julio'!$Q8 -> 407.5 | S8: ='Junio-Julio'!$R8-'Junio-Julio'!$O8 -> 219.4 | T8: =(('Junio-Julio'!$Q8-'Junio-Julio'!$P8)/'Junio-Julio'!$P8) -> 1.1664009 | U8: =(('Junio-Julio'!$Q8-'Junio-Julio'!$P8)/'Junio-Julio'!$Q8) -> 0.53840491 | V8: link | W8: 1688
A9: Flare leggins | B9: 0.5 | C9: ='Junio-Julio'!$B9*2.2 -> 1.1 | D9: ='Junio-Julio'!$F9*'Junio-Julio'!$B9 -> 15 | E9: ='Junio-Julio'!$D9*2.2 -> 33 | F9: 30 | G9: 4.67 | H9: ='Junio-Julio'!$F9*'Junio-Julio'!$G9 -> 140.1 | I9: ='Junio-Julio'!$H9*0.05 -> 7.005 | J9: ='Junio-Julio'!$H9*0.05 -> 7.005 | K9: =SUM('Junio-Julio'!$H9,'Junio-Julio'!$I9,'Junio-Julio'!$J9) -> 154.11 | L9: =1.4*'Junio-Julio'!$E9 -> 46.2 | M9: ='Junio-Julio'!$E9*$E$26 -> 82.5 | N9: =SUM('Junio-Julio'!$L9,'Junio-Julio'!$M9) -> 128.7 | O9: =SUM('Junio-Julio'!$N9, 'Junio-Julio'!$H9, 'Junio-Julio'!$I9, 'Junio-Julio'!$J9) -> 282.81 | P9: ='Junio-Julio'!$O9/'Junio-Julio'!$F9 -> 9.427 | Q9: 15 | R9: ='Junio-Julio'!$F9*'Junio-Julio'!$Q9 -> 450 | S9: ='Junio-Julio'!$R9-'Junio-Julio'!$O9 -> 167.19 | T9: =(('Junio-Julio'!$Q9-'Junio-Julio'!$P9)/'Junio-Julio'!$P9) -> 0.59117429 | U9: =(('Junio-Julio'!$Q9-'Junio-Julio'!$P9)/'Junio-Julio'!$Q9) -> 0.37153333 | V9: link | W9: 1688
A10: Cinturon Gym | B10: 0.4 | C10: ='Junio-Julio'!$B10*2.2 -> 0.88 | D10: ='Junio-Julio'!$F10*'Junio-Julio'!$B10 -> 4.8 | E10: ='Junio-Julio'!$D10*2.2 -> 10.56 | F10: 12 | G10: 3.77 | H10: ='Junio-Julio'!$F10*'Junio-Julio'!$G10 -> 45.24 | I10: ='Junio-Julio'!$H10*0.05 -> 2.262 | J10: ='Junio-Julio'!$H10*0.05 -> 2.262 | K10: =SUM('Junio-Julio'!$H10,'Junio-Julio'!$I10,'Junio-Julio'!$J10) -> 49.764 | L10: =1.4*'Junio-Julio'!$E10 -> 14.784 | M10: ='Junio-Julio'!$E10*$E$26 -> 26.4 | N10: =SUM('Junio-Julio'!$L10,'Junio-Julio'!$M10) -> 41.184 | O10: =SUM('Junio-Julio'!$N10, 'Junio-Julio'!$H10, 'Junio-Julio'!$I10, 'Junio-Julio'!$J10) -> 90.948 | P10: ='Junio-Julio'!$O10/'Junio-Julio'!$F10 -> 7.579 | Q10: 16.36 | R10: ='Junio-Julio'!$F10*'Junio-Julio'!$Q10 -> 196.32 | S10: ='Junio-Julio'!$R10-'Junio-Julio'!$O10 -> 105.372 | T10: =(('Junio-Julio'!$Q10-'Junio-Julio'!$P10)/'Junio-Julio'!$P10) -> 1.1585961 | U10: =(('Junio-Julio'!$Q10-'Junio-Julio'!$P10)/'Junio-Julio'!$Q10) -> 0.53673594 | V10: Link | W10: 1688
A11: enterizo | B11: 0.3 | C11: ='Junio-Julio'!$B11*2.2 -> 0.66 | D11: ='Junio-Julio'!$F11*'Junio-Julio'!$B11 -> 9 | E11: ='Junio-Julio'!$D11*2.2 -> 19.8 | F11: 30 | G11: 3.01 | H11: ='Junio-Julio'!$F11*'Junio-Julio'!$G11 -> 90.3 | I11: ='Junio-Julio'!$H11*0.05 -> 4.515 | J11: ='Junio-Julio'!$H11*0.05 -> 4.515 | K11: =SUM('Junio-Julio'!$H11,'Junio-Julio'!$I11,'Junio-Julio'!$J11) -> 99.33 | L11: =1.4*'Junio-Julio'!$E11 -> 27.72 | M11: ='Junio-Julio'!$E11*$E$26 -> 49.5 | N11: =SUM('Junio-Julio'!$L11,'Junio-Julio'!$M11) -> 77.22 | O11: =SUM('Junio-Julio'!$N11, 'Junio-Julio'!$H11, 'Junio-Julio'!$I11, 'Junio-Julio'!$J11) -> 176.55 | P11: ='Junio-Julio'!$O11/'Junio-Julio'!$F11 -> 5.885 | Q11: 10 | R11: ='Junio-Julio'!$F11*'Junio-Julio'!$Q11 -> 300 | S11: ='Junio-Julio'!$R11-'Junio-Julio'!$O11 -> 123.45 | T11: =(('Junio-Julio'!$Q11-'Junio-Julio'!$P11)/'Junio-Julio'!$P11) -> 0.69923534 | U11: =(('Junio-Julio'!$Q11-'Junio-Julio'!$P11)/'Junio-Julio'!$Q11) -> 0.4115 | V11: Link | W11: 1688
A12: Chalecos | B12: 0.5 | C12: ='Junio-Julio'!$B12*2.2 -> 1.1 | D12: ='Junio-Julio'!$F12*'Junio-Julio'!$B12 -> 15 | E12: ='Junio-Julio'!$D12*2.2 -> 33 | F12: 30 | G12: 5.06 | H12: ='Junio-Julio'!$F12*'Junio-Julio'!$G12 -> 151.8 | I12: ='Junio-Julio'!$H12*0.05 -> 7.59 | J12: ='Junio-Julio'!$H12*0.05 -> 7.59 | K12: =SUM('Junio-Julio'!$H12,'Junio-Julio'!$I12,'Junio-Julio'!$J12) -> 166.98 | L12: =1.4*'Junio-Julio'!$E12 -> 46.2 | M12: ='Junio-Julio'!$E12*$E$26 -> 82.5 | N12: =SUM('Junio-Julio'!$L12,'Junio-Julio'!$M12) -> 128.7 | O12: =SUM('Junio-Julio'!$N12, 'Junio-Julio'!$H12, 'Junio-Julio'!$I12, 'Junio-Julio'!$J12) -> 295.68 | P12: ='Junio-Julio'!$O12/'Junio-Julio'!$F12 -> 9.856 | Q12: 13.63 | R12: ='Junio-Julio'!$F12*'Junio-Julio'!$Q12 -> 408.9 | S12: ='Junio-Julio'!$R12-'Junio-Julio'!$O12 -> 113.22 | T12: =(('Junio-Julio'!$Q12-'Junio-Julio'!$P12)/'Junio-Julio'!$P12) -> 0.38291396 | U12: =(('Junio-Julio'!$Q12-'Junio-Julio'!$P12)/'Junio-Julio'!$Q12) -> 0.27688922 | V12: link | W12: 1688
A13: Camisa de compresion manga larga | B13: 0.3 | C13: ='Junio-Julio'!$B13*2.2 -> 0.66 | D13: ='Junio-Julio'!$F13*'Junio-Julio'!$B13 -> 9 | E13: ='Junio-Julio'!$D13*2.2 -> 19.8 | F13: 30 | G13: 2 | H13: ='Junio-Julio'!$F13*'Junio-Julio'!$G13 -> 60 | I13: ='Junio-Julio'!$H13*0.05 -> 3 | J13: ='Junio-Julio'!$H13*0.05 -> 3 | K13: =SUM('Junio-Julio'!$H13,'Junio-Julio'!$I13,'Junio-Julio'!$J13) -> 66 | L13: =1.4*'Junio-Julio'!$E13 -> 27.72 | M13: ='Junio-Julio'!$E13*$E$26 -> 49.5 | N13: =SUM('Junio-Julio'!$L13,'Junio-Julio'!$M13) -> 77.22 | O13: =SUM('Junio-Julio'!$N13, 'Junio-Julio'!$H13, 'Junio-Julio'!$I13, 'Junio-Julio'!$J13) -> 143.22 | P13: ='Junio-Julio'!$O13/'Junio-Julio'!$F13 -> 4.774 | Q13: 8.15 | R13: ='Junio-Julio'!$F13*'Junio-Julio'!$Q13 -> 244.5 | S13: ='Junio-Julio'!$R13-'Junio-Julio'!$O13 -> 101.28 | T13: =(('Junio-Julio'!$Q13-'Junio-Julio'!$P13)/'Junio-Julio'!$P13) -> 0.7071638 | U13: =(('Junio-Julio'!$Q13-'Junio-Julio'!$P13)/'Junio-Julio'!$Q13) -> 0.41423313 | V13: Link | W13: 1689
A14: Espacio libre (De esto hablamos mañana)
A15: Total | B15: =SUM(B8:B13) -> 2.2 | C15: ='Junio-Julio'!$B15*2.2 -> 4.84 | D15: =SUM(D8:D13) -> 62.8 | E15: =SUM(E8:E13) -> 138.16 | F15: =SUM(F8:F13) -> 182 | G15: =SUM(G8:G13) -> 20.37 | H15: =SUM(H8:H13) -> 580.44 | I15: ='Junio-Julio'!$H15*0.05 -> 29.022 | J15: ='Junio-Julio'!$H15*0.05 -> 29.022 | K15: =SUM('Junio-Julio'!$H15,'Junio-Julio'!$I15,'Junio-Julio'!$J15) -> 638.484 | L15: =SUM(L8:L13) -> 193.424 | M15: =SUM(M8:M13) -> 345.4 | N15: =SUM(N8:N13) -> 538.824 | O15: =SUM(O8:O13) -> 1177.308 | P15: =SUM(P8:P13) -> 41.283 | Q15: =SUM(Q8:Q13) -> 71.29 | R15: =SUM(R8:R13) -> 2007.22 | S15: =SUM(S8:S13) -> 829.912
A24: Concepto | B24: Monto (USD)
A25: Ingresos totales por ventas | B25: =R15 -> 2007.22 | D25: COSTOS x libra | E25: Cantidad (Dólares)
D26: Envío de productos (USA-NIC) | E26: 2.5
A27: Costos de operación | D27: Envío de productos (CHN-USA) | E27: 1. 4
A28: - Costo total de productos | B28: =SUM(K8:K13) -> 638.484
A29: - Costo total de envío | B29: =SUM(N8:N13) -> 538.824
A30: - Gastos de marketing/publicidad
A31: Costo total de la operación | B31: =SUM(B28:B30) -> 1177.308
A33: Utilidad bruta | B33: =B25-B28-B29 -> 829.912
A34: Utilidad neta | B34: =B33-B30 -> 829.912
A36: Márgenes
A37: - Margen bruto sobre ingresos (%) | B37: =B33/B25 -> 0.4134634
A38: - Margen neto sobre ingresos (%) | B38: =B34/B25 -> 0.4134634
A39: - Margen neto sobre costos totales (%) | B39: =B34/B31 -> 0.70492344

Sheet Posible inversion
F5: Cambio oficial dólar a códoba | G5: 36.62
A6: TABLA DE COSTOS
A7: Producto | B7: Peso del producto en Kg | C7: Peso Unitario (libras) | D7: Peso total en Kg | E7: Peso total (libras) | F7: Cantidad | G7: Costo Unitario ($) | H7: Costo Total | I7: comisión sobre transacción | J7: costo de envío interno en china | K7: Costo total total al almacen | L7: Costo Envío China-USA | M7: Costo Envío USA-NIC ($) | N7: Costo envío Total ($) | O7: Costo Total Lote ($) | P7: Costo Unitario NIC | Q7: Precio de venta | R7: Ingreso total por producto | S7: utilidad por producto | T7: margen sobre costros por producto | U7: margen sobre ventas por productos | V7: Links | W7: Origen
A8: Mouse Ergonomico | B8: 0.25 | C8: ='Posible inversion'!$B8*2.2 -> 0.55 | D8: ='Posible inversion'!$F8*'Posible inversion'!$B8 -> 3.75 | E8: ='Posible inversion'!$D8*2.2 -> 8.25 | F8: 15 | G8: 7.58 | H8: ='Posible inversion'!$F8*'Posible inversion'!$G8 -> 113.7 | I8: ='Posible inversion'!$H8*0.0295 -> 3.35415 | J8: ='Posible inversion'!$H8*0.03 -> 3.411 | K8: =SUM('Posible inversion'!$H8,'Posible inversion'!$I8,'Posible inversion'!$J8) -> 120.46515 | L8: =1.4*'Posible inversion'!$E8 -> 11.55 | M8: ='Posible inversion'!$E8*$E$31 -> 20.625 | N8: =SUM('Posible inversion'!$L8,'Posible inversion'!$M8) -> 32.175 | O8: =SUM('Posible inversion'!$N8, 'Posible inversion'!$H8, 'Posible inversion'!$I8, 'Posible inversion'!$J8) -> 152.64015 | P8: ='Posible inversion'!$O8/'Posible inversion'!$F8 -> 10.17601 | Q8: 20.39 | R8: ='Posible inversion'!$F8*'Posible inversion'!$Q8 -> 305.85 | S8: ='Posible inversion'!$R8-'Posible inversion'!$O8 -> 153.20985 | T8: =(('Posible inversion'!$Q8-'Posible inversion'!$P8)/'Posible inversion'!$P8) -> 1.0037323 | U8: =(('Posible inversion'!$Q8-'Posible inversion'!$P8)/'Posible inversion'!$Q8) -> 0.50093134 | V8: link | W8: Alibaba
A9: Audifonos de natacion | B9: 0.23 | C9: ='Posible inversion'!$B9*2.2 -> 0.506 | D9: ='Posible inversion'!$F9*'Posible inversion'!$B9 -> 4.6 | E9: ='Posible inversion'!$D9*2.2 -> 10.12 | F9: 20 | G9: 16.6 | H9: ='Posible inversion'!$F9*'Posible inversion'!$G9 -> 332 | I9: ='Posible inversion'!$H9*0.0295 -> 9.794 | J9: ='Posible inversion'!$H9*0.03 -> 9.96 | K9: =SUM('Posible inversion'!$H9,'Posible inversion'!$I9,'Posible inversion'!$J9) -> 351.754 | L9: =1.4*'Posible inversion'!$E9 -> 14.168 | M9: ='Posible inversion'!$E9*$E$31 -> 25.3 | N9: =SUM('Posible inversion'!$L9,'Posible inversion'!$M9) -> 39.468 | O9: =SUM('Posible inversion'!$N9, 'Posible inversion'!$H9, 'Posible inversion'!$I9, 'Posible inversion'!$J9) -> 391.222 | P9: ='Posible inversion'!$O9/'Posible inversion'!$F9 -> 19.5611 | Q9: 40.79 | R9: ='Posible inversion'!$F9*'Posible inversion'!$Q9 -> 815.8 | S9: ='Posible inversion'!$R9-'Posible inversion'!$O9 -> 424.578 | T9: =(('Posible inversion'!$Q9-'Posible inversion'!$P9)/'Posible inversion'!$P9) -> 1.0852611 | U9: =(('Posible inversion'!$Q9-'Posible inversion'!$P9)/'Posible inversion'!$Q9) -> 0.52044374 | V9: Link | W9: Alibaba
A10: Headphones | B10: 0.4 | C10: ='Posible inversion'!$B10*2.2 -> 0.88 | D10: ='Posible inversion'!$F10*'Posible inversion'!$B10 -> 6 | E10: ='Posible inversion'!$D10*2.2 -> 13.2 | F10: 15 | G10: 3.45 | H10: ='Posible inversion'!$F10*'Posible inversion'!$G10 -> 51.75 | I10: ='Posible inversion'!$H10*0.0295 -> 1.526625 | J10: ='Posible inversion'!$H10*0.03 -> 1.5525 | K10: =SUM('Posible inversion'!$H10,'Posible inversion'!$I10,'Posible inversion'!$J10) -> 54.829125 | L10: =1.4*'Posible inversion'!$E10 -> 18.48 | M10: ='Posible inversion'!$E10*$E$31 -> 33 | N10: =SUM('Posible inversion'!$L10,'Posible inversion'!$M10) -> 51.48 | O10: =SUM('Posible inversion'!$N10, 'Posible inversion'!$H10, 'Posible inversion'!$I10, 'Posible inversion'!$J10) -> 106.30912 | P10: ='Posible inversion'!$O10/'Posible inversion'!$F10 -> 7.087275 | Q10: 16.17 | R10: ='Posible inversion'!$F10*'Posible inversion'!$Q10 -> 242.55 | S10: ='Posible inversion'!$R10-'Posible inversion'!$O10 -> 136.24087 | T10: =(('Posible inversion'!$Q10-'Posible inversion'!$P10)/'Posible inversion'!$P10) -> 1.2815539 | U10: =(('Posible inversion'!$Q10-'Posible inversion'!$P10)/'Posible inversion'!$Q10) -> 0.56170223 | V10: https://detail.1688.com/offer/891194971739.html?offerId=891194971739&hotSaleSkuId=5906548623983&spm=a260k.home2025.recommendpart.32 | W10: 1688
A11: Bandas de ejercicio | B11: 0.01 | C11: ='Posible inversion'!$B11*2.2 -> 0.022 | D11: ='Posible inversion'!$F11*'Posible inversion'!$B11 -> 0.2 | E11: ='Posible inversion'!$D11*2.2 -> 0.44 | F11: 20 | G11: 3.45 | H11: ='Posible inversion'!$F11*'Posible inversion'!$G11 -> 69 | I11: ='Posible inversion'!$H11*0.0295 -> 2.0355 | J11: ='Posible inversion'!$H11*0.03 -> 2.07 | K11: =SUM('Posible inversion'!$H11,'Posible inversion'!$I11,'Posible inversion'!$J11) -> 73.1055 | L11: =1.4*'Posible inversion'!$E11 -> 0.616 | M11: ='Posible inversion'!$E11*$E$31 -> 1.1 | N11: =SUM('Posible inversion'!$L11,'Posible inversion'!$M11) -> 1.716 | O11: =SUM('Posible inversion'!$N11, 'Posible inversion'!$H11, 'Posible inversion'!$I11, 'Posible inversion'!$J11) -> 74.8215 | P11: ='Posible inversion'!$O11/'Posible inversion'!$F11 -> 3.741075 | Q11: 17.17 | R11: ='Posible inversion'!$F11*'Posible inversion'!$Q11 -> 343.4 | S11: ='Posible inversion'!$R11-'Posible inversion'!$O11 -> 268.5785 | T11: =(('Posible inversion'!$Q11-'Posible inversion'!$P11)/'Posible inversion'!$P11) -> 3.5895899 | U11: =(('Posible inversion'!$Q11-'Posible inversion'!$P11)/'Posible inversion'!$Q11) -> 0.78211561 | V11: Link | W11: Alibaba
A12: smartwatch | B12: 0.2 | C12: ='Posible inversion'!$B12*2.2 -> 0.44 | D12: ='Posible inversion'!$F12*'Posible inversion'!$B12 -> 1.2 | E12: ='Posible inversion'!$D12*2.2 -> 2.64 | F12: 6 | G12: 7 | H12: ='Posible inversion'!$F12*'Posible inversion'!$G12 -> 42 | I12: ='Posible inversion'!$H12*0.0295 -> 1.239 | J12: ='Posible inversion'!$H12*0.03 -> 1.26 | K12: =SUM('Posible inversion'!$H12,'Posible inversion'!$I12,'Posible inversion'!$J12) -> 44.499 | L12: =1.4*'Posible inversion'!$E12 -> 3.696 | M12: ='Posible inversion'!$E12*$E$31 -> 6.6 | N12: =SUM('Posible inversion'!$L12,'Posible inversion'!$M12) -> 10.296 | O12: =SUM('Posible inversion'!$N12, 'Posible inversion'!$H12, 'Posible inversion'!$I12, 'Posible inversion'!$J12) -> 54.795 | P12: ='Posible inversion'!$O12/'Posible inversion'!$F12 -> 9.1325 | Q12: 20 | R12: ='Posible inversion'!$F12*'Posible inversion'!$Q12 -> 120 | S12: ='Posible inversion'!$R12-'Posible inversion'!$O12 -> 65.205 | T12: =(('Posible inversion'!$Q12-'Posible inversion'!$P12)/'Posible inversion'!$P12) -> 1.1899808 | U12: =(('Posible inversion'!$Q12-'Posible inversion'!$P12)/'Posible inversion'!$Q12) -> 0.543375 | V12: Link | W12: Alibaba
A13: Pestañas magneticas | B13: 0.05 | C13: ='Posible inversion'!$B13*2.2 -> 0.11 | D13: ='Posible inversion'!$F13*'Posible inversion'!$B13 -> 0.75 | E13: ='Posible inversion'!$D13*2.2 -> 1.65 | F13: 15 | G13: 2.5 | H13: ='Posible inversion'!$F13*'Posible inversion'!$G13 -> 37.5 | I13: ='Posible inversion'!$H13*0.0295 -> 1.10625 | J13: ='Posible inversion'!$H13*0.03 -> 1.125 | K13: =SUM('Posible inversion'!$H13,'Posible inversion'!$I13,'Posible inversion'!$J13) -> 39.73125 | L13: =1.4*'Posible inversion'!$E13 -> 2.31 | M13: ='Posible inversion'!$E13*$E$31 -> 4.125 | N13: =SUM('Posible inversion'!$L13,'Posible inversion'!$M13) -> 6.435 | O13: =SUM('Posible inversion'!$N13, 'Posible inversion'!$H13, 'Posible inversion'!$I13, 'Posible inversion'!$J13) -> 46.16625 | P13: ='Posible inversion'!$O13/'Posible inversion'!$F13 -> 3.07775 | Q13: 7 | R13: ='Posible inversion'!$F13*'Posible inversion'!$Q13 -> 105 | S13: ='Posible inversion'!$R13-'Posible inversion'!$O13 -> 58.83375 | T13: =(('Posible inversion'!$Q13-'Posible inversion'!$P13)/'Posible inversion'!$P13) -> 1.2743888 | U13: =(('Posible inversion'!$Q13-'Posible inversion'!$P13)/'Posible inversion'!$Q13) -> 0.56032143 | V13: Linkk | W13: Alibaba
A14: aspiradora | B14: 0.9 | C14: ='Posible inversion'!$B14*2.2 -> 1.98 | D14: ='Posible inversion'!$F14*'Posible inversion'!$B14 -> 4.5 | E14: ='Posible inversion'!$D14*2.2 -> 9.9 | F14: 5 | G14: 8.5 | H14: ='Posible inversion'!$F14*'Posible inversion'!$G14 -> 42.5 | I14: ='Posible inversion'!$H14*0.0295 -> 1.25375 | J14: ='Posible inversion'!$H14*0.03 -> 1.275 | K14: =SUM('Posible inversion'!$H14,'Posible inversion'!$I14,'Posible inversion'!$J14) -> 45.02875 | L14: =1.4*'Posible inversion'!$E14 -> 13.86 | M14: ='Posible inversion'!$E14*$E$31 -> 24.75 | N14: =SUM('Posible inversion'!$L14,'Posible inversion'!$M14) -> 38.61 | O14: =SUM('Posible inversion'!$N14, 'Posible inversion'!$H14, 'Posible inversion'!$I14, 'Posible inversion'!$J14) -> 83.63875 | P14: ='Posible inversion'!$O14/'Posible inversion'!$F14 -> 16.72775 | Q14: 32.57 | R14: ='Posible inversion'!$F14*'Posible inversion'!$Q14 -> 162.85 | S14: ='Posible inversion'!$R14-'Posible inversion'!$O14 -> 79.21125 | T14: =(('Posible inversion'!$Q14-'Posible inversion'!$P14)/'Posible inversion'!$P14) -> 0.94706401 | U14: =(('Posible inversion'!$Q14-'Posible inversion'!$P14)/'Posible inversion'!$Q14) -> 0.4864062 | V14: link | W14: Alibaba
A15: Inflador Portatil | B15: 0.65 | C15: ='Posible inversion'!$B15*2.2 -> 1.43 | D15: ='Posible inversion'!$F15*'Posible inversion'!$B15 -> 9.75 | E15: ='Posible inversion'!$D15*2.2 -> 21.45 | F15: 15 | G15: 8.88 | H15: ='Posible inversion'!$F15*'Posible inversion'!$G15 -> 133.2 | I15: ='Posible inversion'!$H15*0.0295 -> 3.9294 | J15: ='Posible inversion'!$H15*0.03 -> 3.996 | K15: =SUM('Posible inversion'!$H15,'Posible inversion'!$I15,'Posible inversion'!$J15) -> 141.1254 | L15: =1.4*'Posible inversion'!$E15 -> 30.03 | M15: ='Posible inversion'!$E15*$E$31 -> 53.625 | N15: =SUM('Posible inversion'!$L15,'Posible inversion'!$M15) -> 83.655 | O15: =SUM('Posible inversion'!$N15, 'Posible inversion'!$H15, 'Posible inversion'!$I15, 'Posible inversion'!$J15) -> 224.7804 | P15: ='Posible inversion'!$O15/'Posible inversion'!$F15 -> 14.98536 | Q15: 25 | R15: ='Posible inversion'!$F15*'Posible inversion'!$Q15 -> 375 | S15: ='Posible inversion'!$R15-'Posible inversion'!$O15 -> 150.2196 | T15: =(('Posible inversion'!$Q15-'Posible inversion'!$P15)/'Posible inversion'!$P15) -> 0.66829492 | U15: =(('Posible inversion'!$Q15-'Posible inversion'!$P15)/'Posible inversion'!$Q15) -> 0.4005856 | V15: https://www.alibaba.com/product-detail/New-32L-min-Tire-Inflator-Portable_1601636634534.html?spm=a2700.prosearch.normal_offer.d_image.1a7867afpGVX9R&priceId=ba374b1e14ca487caf51aec51ae4ee9e | W15: Alibaba
A17: Total | B17: =SUM(B8:B16) -> 2.69 | C17: =SUM(C8:C16) -> 5.918 | D17: 35 | E17: =SUM(E8:E16) -> 67.65 | F17: =SUM(F8:F16) -> 111 | G17: =SUM(G8:G16) -> 57.96 | H17: =SUM(H8:H16) -> 821.65 | I17: ='Posible inversion'!$H17*0.0295 -> 24.238675 | J17: ='Posible inversion'!$H17*0.03 -> 24.6495 | K17: =SUM('Posible inversion'!$H17,'Posible inversion'!$I17,'Posible inversion'!$J17) -> 870.53818 | L17: =SUM(L8:L16) -> 94.71 | M17: =SUM(M8:M16) -> 169.125 | N17: =SUM(N8:N16) -> 263.835 | O17: =SUM(O8:O16) -> 1134.3732 | P17: =SUM(P8:P16) -> 84.48882 | Q17: =SUM(Q8:Q16) -> 179.09 | R17: =SUM(R8:R16) -> 2470.45 | S17: =SUM(S8:S16) -> 1336.0768
A29: Concepto | B29: Monto (USD)
A30: Ingresos totales por ventas | B30: =R17 -> 2470.45 | D30: COSTOS x libra | E30: Cantidad (Dólares)
D31: Envío de productos (USA-NIC) | E31: 2.5
A32: Costos de operación | D32: Envío de productos (CHN-USA) | E32: 1. 4
A33: - Costo total de productos | B33: =SUM(K8:K15) -> 870.53818
A34: - Costo total de envío | B34: =SUM(N8:N15) -> 263.835
A35: - Gastos de marketing/publicidad
A36: Costo total de la operación | B36: =SUM(B33:B35) -> 1134.3732
A38: Utilidad bruta | B38: =B30-B33-B34 -> 1336.0768 | H38: compression sockings 15-20mmHg | I38: beige | J38: black
A39: Utilidad neta | B39: =B38-B35 -> 1336.0768 | H39: s | I39: 2 | J39: 2
H40: m | I40: 3 | J40: 3
A41: Márgenes | H41: total | I41: 5 | J41: 5
A42: - Margen bruto sobre ingresos (%) | B42: =B38/B30 -> 0.54082326
A43: - Margen neto sobre ingresos (%) | B43: =B39/B30 -> 0.54082326
A44: - Margen neto sobre costos totales (%) | B44: =B39/B36 -> 1.1778107
